pyflowgraph/__init__.py
pyflowgraph/connection.py
pyflowgraph/graph_view.py
pyflowgraph/graph_view_widget.py
pyflowgraph/mouse_grabber.py
pyflowgraph/node.py
pyflowgraph/port.py
pyflowgraph/selection_rect.py
pyflowgraph-0.0.2.dist-info/DESCRIPTION.rst
pyflowgraph-0.0.2.dist-info/METADATA
pyflowgraph-0.0.2.dist-info/RECORD
pyflowgraph-0.0.2.dist-info/WHEEL
pyflowgraph-0.0.2.dist-info/metadata.json
pyflowgraph-0.0.2.dist-info/top_level.txt
